{
    "words": [
        {
            "Word": "Abdomen",
            "Difficulty": "Normal"
        },
        {
            "Word": "Abolish",
            "Difficulty": "Normal"
        },
        {
            "Word": "Absence",
            "Difficulty": "Normal"
        },
        {
            "Word": "Absorb",
            "Difficulty": "Easy"
        },
        {
            "Word": "Abstract",
            "Difficulty": "Normal"
        },
        {
            "Word": "Agnostic",
            "Difficulty": "Normal"
        },
        {
            "Word": "Albeit",
            "Difficulty": "Normal"
        },
        {
            "Word": "Alliance",
            "Difficulty": "Normal"
        },
        {
            "Word": "Alphabet",
            "Difficulty": "Normal"
        },
        {
            "Word": "Anatomical",
            "Difficulty": "Normal"
        },
        {
            "Word": "Appetite",
            "Difficulty": "Normal"
        },
        {
            "Word": "Armor",
            "Difficulty": "Easy"
        },
        {
            "Word": "Ash",
            "Difficulty": "Easy"
        },
        {
            "Word": "Assumption",
            "Difficulty": "Normal"
        },
        {
            "Word": "Automatic",
            "Difficulty": "Normal"
        },
        {
            "Word": "Await",
            "Difficulty": "Normal"
        },
        {
            "Word": "Bayonet",
            "Difficulty": "Normal"
        },
        {
            "Word": "Bingo",
            "Difficulty": "Easy"
        },
        {
            "Word": "Biography",
            "Difficulty": "Normal"
        },
        {
            "Word": "Bizarre",
            "Difficulty": "Normal"
        },
        {
            "Word": "Brain",
            "Difficulty": "Easy"
        },
        {
            "Word": "Breakthrough",
            "Difficulty": "Normal"
        },
        {
            "Word": "Broccoli",
            "Difficulty": "Normal"
        },
        {
            "Word": "Burger",
            "Difficulty": "Normal"
        },
        {
            "Word": "Burial",
            "Difficulty": "Easy"
        },
        {
            "Word": "Cabin",
            "Difficulty": "Easy"
        },
        {
            "Word": "Chicken",
            "Difficulty": "Normal"
        },
        {
            "Word": "Chronic",
            "Difficulty": "Normal"
        },
        {
            "Word": "Circle",
            "Difficulty": "Normal"
        },
        {
            "Word": "Clever",
            "Difficulty": "Easy"
        },
        {
            "Word": "Cliff",
            "Difficulty": "Easy"
        },
        {
            "Word": "Colonel/Kernel",
            "Difficulty": "Normal"
        },
        {
            "Word": "Comply",
            "Difficulty": "Easy"
        },
        {
            "Word": "Concentration",
            "Difficulty": "Normal"
        },
        {
            "Word": "Congratulate",
            "Difficulty": "Normal"
        },
        {
            "Word": "Controversial",
            "Difficulty": "Normal"
        },
        {
            "Word": "Convey",
            "Difficulty": "Easy"
        },
        {
            "Word": "Cool",
            "Difficulty": "Easy"
        },
        {
            "Word": "Dairy",
            "Difficulty": "Easy"
        },
        {
            "Word": "Debris",
            "Difficulty": "Normal"
        },
        {
            "Word": "Defy",
            "Difficulty": "Easy"
        },
        {
            "Word": "Diesel",
            "Difficulty": "Normal"
        },
        {
            "Word": "Derogatory",
            "Difficulty": "Easy"
        },
        {
            "Word": "Duck",
            "Difficulty": "Easy"
        },
        {
            "Word": "Echo",
            "Difficulty": "Easy"
        },
        {
            "Word": "Embassy",
            "Difficulty": "Normal"
        },
        {
            "Word": "Enact",
            "Difficulty": "Easy"
        },
        {
            "Word": "Erupt",
            "Difficulty": "Easy"
        },
        {
            "Word": "Exert",
            "Difficulty": "Easy"
        },
        {
            "Word": "Exile",
            "Difficulty": "Easy"
        },
        {
            "Word": "Familiar",
            "Difficulty": "Normal"
        },
        {
            "Word": "Film",
            "Difficulty": "Easy"
        },
        {
            "Word": "Filter",
            "Difficulty": "Easy"
        },
        {
            "Word": "Firefighter",
            "Difficulty": "Normal"
        },
        {
            "Word": "Forbid",
            "Difficulty": "Easy"
        },
        {
            "Word": "Formidable",
            "Difficulty": "Normal"
        },
        {
            "Word": "Frolic",
            "Difficulty": "Normal"
        },
        {
            "Word": "Furious",
            "Difficulty": "Normal"
        },
        {
            "Word": "Gallant",
            "Difficulty": "Normal"
        },
        {
            "Word": "Gazebo",
            "Difficulty": "Normal"
        },
        {
            "Word": "Gender",
            "Difficulty": "Easy"
        },
        {
            "Word": "Giant",
            "Difficulty": "Easy"
        },
        {
            "Word": "Gold",
            "Difficulty": "Easy"
        },
        {
            "Word": "Greedy",
            "Difficulty": "Easy"
        },
        {
            "Word": "Grub",
            "Difficulty": "Easy"
        },
        {
            "Word": "Guideline",
            "Difficulty": "Normal"
        },
        {
            "Word": "Heresy",
            "Difficulty": "Normal"
        },
        {
            "Word": "Hotel",
            "Difficulty": "Easy"
        },
        {
            "Word": "House",
            "Difficulty": "Easy"
        },
        {
            "Word": "Human",
            "Difficulty": "Easy"
        },
        {
            "Word": "Hungry",
            "Difficulty": "Easy"
        },
        {
            "Word": "Immobilize/Immobilise",
            "Difficulty": "Normal"
        },
        {
            "Word": "Ink",
            "Difficulty": "Easy"
        },
        {
            "Word": "Integrity",
            "Difficulty": "Normal"
        },
        {
            "Word": "Intent",
            "Difficulty": "Easy"
        },
        {
            "Word": "Intermediate",
            "Difficulty": "Normal"
        },
        {
            "Word": "Ionize/Ionise",
            "Difficulty": "Normal"
        },
        {
            "Word": "Iron",
            "Difficulty": "Easy"
        },
        {
            "Word": "Irony",
            "Difficulty": "Easy"
        },
        {
            "Word": "Lactose",
            "Difficulty": "Normal"
        },
        {
            "Word": "Lather",
            "Difficulty": "Normal"
        },
        {
            "Word": "Length",
            "Difficulty": "Easy"
        },
        {
            "Word": "Zoo",
            "Difficulty": "Easy"
        },
        {
            "Word": "Emoji",
            "Difficulty": "Easy"
        },
        {
            "Word": "Kiss",
            "Difficulty": "Easy"
        },
        {
            "Word": "Liable",
            "Difficulty": "Normal"
        },
        {
            "Word": "Lightning",
            "Difficulty": "Normal"
        },
        {
            "Word": "Limousine",
            "Difficulty": "Normal"
        },
        {
            "Word": "Magnificent",
            "Difficulty": "Normal"
        },
        {
            "Word": "Margin",
            "Difficulty": "Easy"
        },
        {
            "Word": "Meditate",
            "Difficulty": "Normal"
        },
        {
            "Word": "Microorganism",
            "Difficulty": "Normal"
        },
        {
            "Word": "Mix",
            "Difficulty": "Easy"
        },
        {
            "Word": "Monk",
            "Difficulty": "Easy"
        },
        {
            "Word": "Neighboring",
            "Difficulty": "Easy"
        },
        {
            "Word": "Noble/Nobel",
            "Difficulty": "Easy"
        },
        {
            "Word": "Noob",
            "Difficulty": "Easy"
        },
        {
            "Word": "Oasis",
            "Difficulty": "Normal"
        },
        {
            "Word": "Obesity",
            "Difficulty": "Normal"
        },
        {
            "Word": "Offender",
            "Difficulty": "Normal"
        },
        {
            "Word": "Optimism",
            "Difficulty": "Normal"
        },
        {
            "Word": "Overdue/Overdo",
            "Difficulty": "Normal"
        },
        {
            "Word": "Palatine",
            "Difficulty": "Normal"
        },
        {
            "Word": "Paradox",
            "Difficulty": "Normal"
        },
        {
            "Word": "Pear/Pair",
            "Difficulty": "Easy"
        },
        {
            "Word": "Pie",
            "Difficulty": "Easy"
        },
        {
            "Word": "Pasta",
            "Difficulty": "Easy"
        },
        {
            "Word": "Flower",
            "Difficulty": "Easy"
        },
        {
            "Word": "Pigeon",
            "Difficulty": "Normal"
        },
        {
            "Word": "Plethora",
            "Difficulty": "Normal"
        },
        {
            "Word": "Power",
            "Difficulty": "Easy"
        },
        {
            "Word": "Prank",
            "Difficulty": "Easy"
        },
        {
            "Word": "Pray/Prey",
            "Difficulty": "Easy"
        },
        {
            "Word": "Probably",
            "Difficulty": "Normal"
        },
        {
            "Word": "Proclamation",
            "Difficulty": "Normal"
        },
        {
            "Word": "Proof",
            "Difficulty": "Easy"
        },
        {
            "Word": "Quack",
            "Difficulty": "Easy"
        },
        {
            "Word": "Quill",
            "Difficulty": "Normal"
        },
        {
            "Word": "Rally",
            "Difficulty": "Easy"
        },
        {
            "Word": "Wind",
            "Difficulty": "Easy"
        },
        {
            "Word": "Random",
            "Difficulty": "Easy"
        },
        {
            "Word": "Refrain",
            "Difficulty": "Normal"
        },
        {
            "Word": "Refugee",
            "Difficulty": "Normal"
        },
        {
            "Word": "Reply",
            "Difficulty": "Easy"
        },
        {
            "Word": "Robust",
            "Difficulty": "Easy"
        },
        {
            "Word": "Ruby",
            "Difficulty": "Easy"
        },
        {
            "Word": "Rye/Wry",
            "Difficulty": "Normal"
        },
        {
            "Word": "Semicircle",
            "Difficulty": "Normal"
        },
        {
            "Word": "Shake",
            "Difficulty": "Easy"
        },
        {
            "Word": "Sigh",
            "Difficulty": "Easy"
        },
        {
            "Word": "Significance",
            "Difficulty": "Normal"
        },
        {
            "Word": "Size",
            "Difficulty": "Easy"
        },
        {
            "Word": "Soda",
            "Difficulty": "Easy"
        },
        {
            "Word": "State",
            "Difficulty": "Easy"
        },
        {
            "Word": "Stereotype",
            "Difficulty": "Normal"
        },
        {
            "Word": "Still",
            "Difficulty": "Easy"
        },
        {
            "Word": "Strategic",
            "Difficulty": "Normal"
        },
        {
            "Word": "Stumble",
            "Difficulty": "Easy"
        },
        {
            "Word": "Subsidy",
            "Difficulty": "Normal"
        },
        {
            "Word": "Suck",
            "Difficulty": "Easy"
        },
        {
            "Word": "Tank",
            "Difficulty": "Easy"
        },
        {
            "Word": "Syntax",
            "Difficulty": "Normal"
        },
        {
            "Word": "Tangerine",
            "Difficulty": "Normal"
        },
        {
            "Word": "Telepathy",
            "Difficulty": "Normal"
        },
        {
            "Word": "Thesis",
            "Difficulty": "Normal"
        },
        {
            "Word": "Town",
            "Difficulty": "Easy"
        },
        {
            "Word": "Transaction",
            "Difficulty": "Normal"
        },
        {
            "Word": "Trauma",
            "Difficulty": "Easy"
        },
        {
            "Word": "Twist",
            "Difficulty": "Easy"
        },
        {
            "Word": "Uncomfortable",
            "Difficulty": "Normal"
        },
        {
            "Word": "Update",
            "Difficulty": "Easy"
        },
        {
            "Word": "Vague",
            "Difficulty": "Normal"
        },
        {
            "Word": "Vain/Vein",
            "Difficulty": "Easy"
        },
        {
            "Word": "Villain",
            "Difficulty": "Normal"
        },
        {
            "Word": "Voluntary",
            "Difficulty": "Normal"
        },
        {
            "Word": "Water",
            "Difficulty": "Easy"
        },
        {
            "Word": "Word",
            "Difficulty": "Easy"
        },
        {
            "Word": "Workout",
            "Difficulty": "Easy"
        },
        {
            "Word": "Wrist",
            "Difficulty": "Easy"
        },
        {
            "Word": "Abscond",
            "Difficulty": "Normal"
        },
        {
            "Word": "Accomplishment",
            "Difficulty": "Normal"
        },
        {
            "Word": "Accumulation",
            "Difficulty": "Normal"
        },
        {
            "Word": "Aerodynamic",
            "Difficulty": "Normal"
        },
        {
            "Word": "Window",
            "Difficulty": "Normal"
        },
        {
            "Word": "Heritage",
            "Difficulty": "Normal"
        },
        {
            "Word": "Aggrandize/Aggrandise",
            "Difficulty": "Hard"
        },
        {
            "Word": "Agriculture",
            "Difficulty": "Normal"
        },
        {
            "Word": "Bronchitis",
            "Difficulty": "Normal"
        },
        {
            "Word": "Ambiguous",
            "Difficulty": "Hard"
        },
        {
            "Word": "Anaphylactic",
            "Difficulty": "Hard"
        },
        {
            "Word": "Anemone",
            "Difficulty": "Normal"
        },
        {
            "Word": "Articulate",
            "Difficulty": "Normal"
        },
        {
            "Word": "Asthma",
            "Difficulty": "Normal"
        },
        {
            "Word": "Attorney",
            "Difficulty": "Hard"
        },
        {
            "Word": "Bandeau",
            "Difficulty": "Hard"
        },
        {
            "Word": "Benevolence",
            "Difficulty": "Normal"
        },
        {
            "Word": "Enchantment",
            "Difficulty": "Normal"
        },
        {
            "Word": "Beneficiary",
            "Difficulty": "Normal"
        },
        {
            "Word": "Brusque",
            "Difficulty": "Hard"
        },
        {
            "Word": "Catalogue",
            "Difficulty": "Normal"
        },
        {
            "Word": "Caustic",
            "Difficulty": "Normal"
        },
        {
            "Word": "Charisma",
            "Difficulty": "Normal"
        },
        {
            "Word": "Champagne",
            "Difficulty": "Normal"
        },
        {
            "Word": "Chlorophyll",
            "Difficulty": "Normal"
        },
        {
            "Word": "Coalescence",
            "Difficulty": "Hard"
        },
        {
            "Word": "Cognitive",
            "Difficulty": "Normal"
        },
        {
            "Word": "Aspiration",
            "Difficulty": "Normal"
        },
        {
            "Word": "Combustible",
            "Difficulty": "Normal"
        },
        {
            "Word": "Commodity",
            "Difficulty": "Normal"
        },
        {
            "Word": "Surrogate",
            "Difficulty": "Normal"
        },
        {
            "Word": "Technological",
            "Difficulty": "Normal"
        },
        {
            "Word": "Center",
            "Difficulty": "Normal"
        },
        {
            "Word": "Melancholy",
            "Difficulty": "Normal"
        },
        {
            "Word": "Compunction",
            "Difficulty": "Hard"
        },
        {
            "Word": "Curious",
            "Difficulty": "Normal"
        },
        {
            "Word": "Dauntless",
            "Difficulty": "Normal"
        },
        {
            "Word": "Deleterious",
            "Difficulty": "Hard"
        },
        {
            "Word": "Deployment",
            "Difficulty": "Normal"
        },
        {
            "Word": "Wednesday",
            "Difficulty": "Normal"
        },
        {
            "Word": "Dilate",
            "Difficulty": "Normal"
        },
        {
            "Word": "Disappointment",
            "Difficulty": "Normal"
        },
        {
            "Word": "Doctrine",
            "Difficulty": "Normal"
        },
        {
            "Word": "Atmospheric",
            "Difficulty": "Normal"
        },
        {
            "Word": "Rhythm",
            "Difficulty": "Normal"
        },
        {
            "Word": "Dolphin",
            "Difficulty": "Normal"
        },
        {
            "Word": "Elaborate",
            "Difficulty": "Normal"
        },
        {
            "Word": "Elysian/Elision",
            "Difficulty": "Hard"
        },
        {
            "Word": "Encore",
            "Difficulty": "Normal"
        },
        {
            "Word": "Endeavor",
            "Difficulty": "Normal"
        },
        {
            "Word": "Epiphany",
            "Difficulty": "Normal"
        },
        {
            "Word": "Erratic",
            "Difficulty": "Normal"
        },
        {
            "Word": "Euphoria",
            "Difficulty": "Normal"
        },
        {
            "Word": "Excellent",
            "Difficulty": "Normal"
        },
        {
            "Word": "Excalibur",
            "Difficulty": "Normal"
        },
        {
            "Word": "Expenditure",
            "Difficulty": "Normal"
        },
        {
            "Word": "Sniffle",
            "Difficulty": "Normal"
        },
        {
            "Word": "Exponential",
            "Difficulty": "Normal"
        },
        {
            "Word": "Favorable",
            "Difficulty": "Normal"
        },
        {
            "Word": "Cooking",
            "Difficulty": "Normal"
        },
        {
            "Word": "Fluorescent",
            "Difficulty": "Normal"
        },
        {
            "Word": "Flamboyant",
            "Difficulty": "Normal"
        },
        {
            "Word": "Twenty",
            "Difficulty": "Normal"
        },
        {
            "Word": "Flavor/Flavour",
            "Difficulty": "Normal"
        },
        {
            "Word": "Forthcoming",
            "Difficulty": "Normal"
        },
        {
            "Word": "Betray",
            "Difficulty": "Normal"
        },
        {
            "Word": "Residential",
            "Difficulty": "Normal"
        },
        {
            "Word": "Gastronomic",
            "Difficulty": "Normal"
        },
        {
            "Word": "Gibberish",
            "Difficulty": "Normal"
        },
        {
            "Word": "Adolescent",
            "Difficulty": "Normal"
        },
        {
            "Word": "Glaucomatous",
            "Difficulty": "Hard"
        },
        {
            "Word": "Gradual",
            "Difficulty": "Normal"
        },
        {
            "Word": "Heterozygous",
            "Difficulty": "Hard"
        },
        {
            "Word": "Hornswoggle",
            "Difficulty": "Normal"
        },
        {
            "Word": "Crowd",
            "Difficulty": "Normal"
        },
        {
            "Word": "Hexagonal",
            "Difficulty": "Normal"
        },
        {
            "Word": "Exaggerate",
            "Difficulty": "Normal"
        },
        {
            "Word": "Methodology",
            "Difficulty": "Normal"
        },
        {
            "Word": "Notorious",
            "Difficulty": "Normal"
        },
        {
            "Word": "Humanitarian",
            "Difficulty": "Normal"
        },
        {
            "Word": "Hypothesis",
            "Difficulty": "Normal"
        },
        {
            "Word": "Ideological",
            "Difficulty": "Normal"
        },
        {
            "Word": "Imminent",
            "Difficulty": "Normal"
        },
        {
            "Word": "Special",
            "Difficulty": "Normal"
        },
        {
            "Word": "Imprisonment",
            "Difficulty": "Normal"
        },
        {
            "Word": "Ravenous",
            "Difficulty": "Normal"
        },
        {
            "Word": "Indefatigable",
            "Difficulty": "Hard"
        },
        {
            "Word": "Independence",
            "Difficulty": "Normal"
        },
        {
            "Word": "Indifference",
            "Difficulty": "Normal"
        },
        {
            "Word": "Negotiation",
            "Difficulty": "Normal"
        },
        {
            "Word": "Ingenious",
            "Difficulty": "Hard"
        },
        {
            "Word": "Inhabitant",
            "Difficulty": "Normal"
        },
        {
            "Word": "Juxtaposition",
            "Difficulty": "Normal"
        },
        {
            "Word": "Legendary",
            "Difficulty": "Normal"
        },
        {
            "Word": "Macabre",
            "Difficulty": "Hard"
        },
        {
            "Word": "Mathematician",
            "Difficulty": "Normal"
        },
        {
            "Word": "Misconception",
            "Difficulty": "Normal"
        },
        {
            "Word": "Municipal",
            "Difficulty": "Hard"
        },
        {
            "Word": "Necromancer",
            "Difficulty": "Normal"
        },
        {
            "Word": "Secret",
            "Difficulty": "Normal"
        },
        {
            "Word": "Intermission",
            "Difficulty": "Normal"
        },
        {
            "Word": "Nonplussed",
            "Difficulty": "Normal"
        },
        {
            "Word": "Obituary",
            "Difficulty": "Normal"
        },
        {
            "Word": "Oblivious",
            "Difficulty": "Normal"
        },
        {
            "Word": "Opaque",
            "Difficulty": "Normal"
        },
        {
            "Word": "Normal",
            "Difficulty": "Normal"
        },
        {
            "Word": "Parallel",
            "Difficulty": "Normal"
        },
        {
            "Word": "Walnut",
            "Difficulty": "Normal"
        },
        {
            "Word": "Participation",
            "Difficulty": "Normal"
        },
        {
            "Word": "Powder",
            "Difficulty": "Normal"
        },
        {
            "Word": "Passionate",
            "Difficulty": "Normal"
        },
        {
            "Word": "Password",
            "Difficulty": "Normal"
        },
        {
            "Word": "Embarrassment",
            "Difficulty": "Normal"
        },
        {
            "Word": "Peppermint",
            "Difficulty": "Normal"
        },
        {
            "Word": "Periodically",
            "Difficulty": "Normal"
        },
        {
            "Word": "Personnel",
            "Difficulty": "Normal"
        },
        {
            "Word": "Pestilence",
            "Difficulty": "Normal"
        },
        {
            "Word": "Pharaoh/Farrow",
            "Difficulty": "Hard"
        },
        {
            "Word": "Phlegm",
            "Difficulty": "Hard"
        },
        {
            "Word": "Photographer",
            "Difficulty": "Normal"
        },
        {
            "Word": "Pirouette",
            "Difficulty": "Hard"
        },
        {
            "Word": "Plenipotentiary",
            "Difficulty": "Hard"
        },
        {
            "Word": "Pomegranate",
            "Difficulty": "Normal"
        },
        {
            "Word": "Portfolio",
            "Difficulty": "Normal"
        },
        {
            "Word": "Predecessor",
            "Difficulty": "Normal"
        },
        {
            "Word": "Predominantly",
            "Difficulty": "Normal"
        },
        {
            "Word": "Procrastinate",
            "Difficulty": "Normal"
        },
        {
            "Word": "Pronunciation",
            "Difficulty": "Normal"
        },
        {
            "Word": "Propaganda",
            "Difficulty": "Normal"
        },
        {
            "Word": "Pursuit",
            "Difficulty": "Normal"
        },
        {
            "Word": "Recession",
            "Difficulty": "Normal"
        },
        {
            "Word": "Recipient",
            "Difficulty": "Normal"
        },
        {
            "Word": "Reincarnation",
            "Difficulty": "Normal"
        },
        {
            "Word": "Reliability",
            "Difficulty": "Normal"
        },
        {
            "Word": "Gobbledygook",
            "Difficulty": "Normal"
        },
        {
            "Word": "Detrimental",
            "Difficulty": "Normal"
        },
        {
            "Word": "Remarkable",
            "Difficulty": "Normal"
        },
        {
            "Word": "Reminiscence",
            "Difficulty": "Hard"
        },
        {
            "Word": "Sapphire",
            "Difficulty": "Normal"
        },
        {
            "Word": "Sabotage",
            "Difficulty": "Normal"
        },
        {
            "Word": "Sashay/Sachet",
            "Difficulty": "Normal"
        },
        {
            "Word": "Scholarship",
            "Difficulty": "Normal"
        },
        {
            "Word": "Scrutiny",
            "Difficulty": "Normal"
        },
        {
            "Word": "Kangaroo",
            "Difficulty": "Normal"
        },
        {
            "Word": "Seldom",
            "Difficulty": "Normal"
        },
        {
            "Word": "Syllable",
            "Difficulty": "Normal"
        },
        {
            "Word": "Akin",
            "Difficulty": "Normal"
        },
        {
            "Word": "Sentimental",
            "Difficulty": "Normal"
        },
        {
            "Word": "Separation",
            "Difficulty": "Normal"
        },
        {
            "Word": "Sequacious",
            "Difficulty": "Hard"
        },
        {
            "Word": "Shareholder",
            "Difficulty": "Normal"
        },
        {
            "Word": "Solidarity",
            "Difficulty": "Normal"
        },
        {
            "Word": "Spokesperson",
            "Difficulty": "Normal"
        },
        {
            "Word": "Steadfast",
            "Difficulty": "Normal"
        },
        {
            "Word": "Supposedly",
            "Difficulty": "Normal"
        },
        {
            "Word": "Surveillance",
            "Difficulty": "Normal"
        },
        {
            "Word": "Susceptible",
            "Difficulty": "Normal"
        },
        {
            "Word": "Syllepsis",
            "Difficulty": "Hard"
        },
        {
            "Word": "Symmetrical",
            "Difficulty": "Normal"
        },
        {
            "Word": "Ricochet",
            "Difficulty": "Normal"
        },
        {
            "Word": "Systematic",
            "Difficulty": "Normal"
        },
        {
            "Word": "Thesaurus",
            "Difficulty": "Normal"
        },
        {
            "Word": "Translucent",
            "Difficulty": "Normal"
        },
        {
            "Word": "Transparency",
            "Difficulty": "Normal"
        },
        {
            "Word": "Transportation",
            "Difficulty": "Normal"
        },
        {
            "Word": "Tremendous",
            "Difficulty": "Normal"
        },
        {
            "Word": "Uncharacteristic",
            "Difficulty": "Hard"
        },
        {
            "Word": "Unintelligible",
            "Difficulty": "Normal"
        },
        {
            "Word": "Consumption",
            "Difficulty": "Normal"
        },
        {
            "Word": "Unprecedented",
            "Difficulty": "Normal"
        },
        {
            "Word": "Validity",
            "Difficulty": "Normal"
        },
        {
            "Word": "Idiom",
            "Difficulty": "Normal"
        },
        {
            "Word": "Venerate",
            "Difficulty": "Normal"
        },
        {
            "Word": "Violation",
            "Difficulty": "Normal"
        },
        {
            "Word": "Warrior",
            "Difficulty": "Normal"
        },
        {
            "Word": "Worthwhile",
            "Difficulty": "Normal"
        },
        {
            "Word": "Wholeheartedly",
            "Difficulty": "Normal"
        },
        {
            "Word": "Zephyr",
            "Difficulty": "Hard"
        },
        {
            "Word": "Zygote",
            "Difficulty": "Normal"
        },
        {
            "Word": "Bamboo",
            "Difficulty": "Normal"
        },
        {
            "Word": "Abacaxi",
            "Difficulty": "Extreme"
        },
        {
            "Word": "Absquatulate",
            "Difficulty": "Extreme"
        },
        {
            "Word": "Accommodate",
            "Difficulty": "Hard"
        },
        {
            "Word": "Acculturate",
            "Difficulty": "Hard"
        },
        {
            "Word": "Acquiesce",
            "Difficulty": "Extreme"
        },
        {
            "Word": "Aegis",
            "Difficulty": "Extreme"
        },
        {
            "Word": "Agoraphobic",
            "Difficulty": "Hard"
        },
        {
            "Word": "Allotransplantation",
            "Difficulty": "Extreme"
        },
        {
            "Word": "Ambidextrous",
            "Difficulty": "Hard"
        },
        {
            "Word": "Counterintuitive",
            "Difficulty": "Hard"
        },
        {
            "Word": "Defenestration",
            "Difficulty": "Hard"
        },
        {
            "Word": "Chauffeur",
            "Difficulty": "Hard"
        },
        {
            "Word": "Anachronistic",
            "Difficulty": "Extreme"
        },
        {
            "Word": "Antediluvian",
            "Difficulty": "Extreme"
        },
        {
            "Word": "Antidisestablishmentarianism",
            "Difficulty": "Extreme"
        },
        {
            "Word": "Apocryphal",
            "Difficulty": "Extreme"
        },
        {
            "Word": "Asphyxiation",
            "Difficulty": "Hard"
        },
        {
            "Word": "Borborygmus",
            "Difficulty": "Extreme"
        },
        {
            "Word": "Brucellosis",
            "Difficulty": "Hard"
        },
        {
            "Word": "Buckminsterfullerene",
            "Difficulty": "Extreme"
        },
        {
            "Word": "Bucolic",
            "Difficulty": "Hard"
        },
        {
            "Word": "Bureaucracy",
            "Difficulty": "Extreme"
        },
        {
            "Word": "Calamitous",
            "Difficulty": "Hard"
        },
        {
            "Word": "Calumny",
            "Difficulty": "Hard"
        },
        {
            "Word": "Martyrdom",
            "Difficulty": "Hard"
        },
        {
            "Word": "Capoeira",
            "Difficulty": "Extreme"
        },
        {
            "Word": "Capricious",
            "Difficulty": "Extreme"
        },
        {
            "Word": "Captious",
            "Difficulty": "Hard"
        },
        {
            "Word": "Codicil",
            "Difficulty": "Hard"
        },
        {
            "Word": "Astigmatism",
            "Difficulty": "Hard"
        },
        {
            "Word": "Colloquialism",
            "Difficulty": "Hard"
        },
        {
            "Word": "Commodore",
            "Difficulty": "Hard"
        },
        {
            "Word": "Consanguine",
            "Difficulty": "Hard"
        },
        {
            "Word": "Contradistinguish",
            "Difficulty": "Extreme"
        },
        {
            "Word": "Correspondence",
            "Difficulty": "Hard"
        },
        {
            "Word": "Cyrillic",
            "Difficulty": "Extreme"
        },
        {
            "Word": "Dendrochronology",
            "Difficulty": "Extreme"
        },
        {
            "Word": "Deoxyribonucleic",
            "Difficulty": "Extreme"
        },
        {
            "Word": "Depilatory",
            "Difficulty": "Hard"
        },
        {
            "Word": "Dichotomization/Dichotomisation",
            "Difficulty": "Extreme"
        },
        {
            "Word": "Discombobulate",
            "Difficulty": "Hard"
        },
        {
            "Word": "Dodecahedron",
            "Difficulty": "Hard"
        },
        {
            "Word": "Eloquent",
            "Difficulty": "Hard"
        },
        {
            "Word": "Entrepreneur",
            "Difficulty": "Extreme"
        },
        {
            "Word": "Facsimile",
            "Difficulty": "Hard"
        },
        {
            "Word": "Simultaneous",
            "Difficulty": "Hard"
        },
        {
            "Word": "Fjord",
            "Difficulty": "Hard"
        },
        {
            "Word": "Fossiliferous",
            "Difficulty": "Extreme"
        },
        {
            "Word": "Fuchsia",
            "Difficulty": "Extreme"
        },
        {
            "Word": "Gentrification",
            "Difficulty": "Hard"
        },
        {
            "Word": "Glockenspiel",
            "Difficulty": "Hard"
        },
        {
            "Word": "Gubernatorial",
            "Difficulty": "Extreme"
        },
        {
            "Word": "Hierarchy",
            "Difficulty": "Hard"
        },
        {
            "Word": "Hieroglyphics",
            "Difficulty": "Extreme"
        },
        {
            "Word": "Homogeneous",
            "Difficulty": "Hard"
        },
        {
            "Word": "Hypermetropia",
            "Difficulty": "Hard"
        },
        {
            "Word": "Iconoclast",
            "Difficulty": "Extreme"
        },
        {
            "Word": "Incandescent",
            "Difficulty": "Hard"
        },
        {
            "Word": "Clandestine",
            "Difficulty": "Hard"
        },
        {
            "Word": "Inchoate",
            "Difficulty": "Extreme"
        },
        {
            "Word": "Incomprehensibility",
            "Difficulty": "Extreme"
        },
        {
            "Word": "Infinitesimal",
            "Difficulty": "Extreme"
        },
        {
            "Word": "Infundibulum",
            "Difficulty": "Extreme"
        },
        {
            "Word": "Isometropia",
            "Difficulty": "Hard"
        },
        {
            "Word": "Isthmus",
            "Difficulty": "Extreme"
        },
        {
            "Word": "Kaleidoscope",
            "Difficulty": "Hard"
        },
        {
            "Word": "Labyrinthine",
            "Difficulty": "Extreme"
        },
        {
            "Word": "Languid",
            "Difficulty": "Extreme"
        },
        {
            "Word": "Legislation",
            "Difficulty": "Hard"
        },
        {
            "Word": "Lepidopterology",
            "Difficulty": "Extreme"
        },
        {
            "Word": "Liaison",
            "Difficulty": "Hard"
        },
        {
            "Word": "Lexicography",
            "Difficulty": "Hard"
        },
        {
            "Word": "Malapropism",
            "Difficulty": "Hard"
        },
        {
            "Word": "Mellifluous",
            "Difficulty": "Hard"
        },
        {
            "Word": "Menagerie",
            "Difficulty": "Hard"
        },
        {
            "Word": "Milieu",
            "Difficulty": "Extreme"
        },
        {
            "Word": "Minuscule/Miniscule",
            "Difficulty": "Hard"
        },
        {
            "Word": "Monochromatic",
            "Difficulty": "Hard"
        },
        {
            "Word": "Monosyllabic",
            "Difficulty": "Hard"
        },
        {
            "Word": "Myopic",
            "Difficulty": "Hard"
        },
        {
            "Word": "Myriad",
            "Difficulty": "Hard"
        },
        {
            "Word": "Narcissistic",
            "Difficulty": "Hard"
        },
        {
            "Word": "Nauseous",
            "Difficulty": "Hard"
        },
        {
            "Word": "Neuroplasticity",
            "Difficulty": "Hard"
        },
        {
            "Word": "Nutritious",
            "Difficulty": "Hard"
        },
        {
            "Word": "Obfuscation",
            "Difficulty": "Hard"
        },
        {
            "Word": "Onomatopoeia",
            "Difficulty": "Extreme"
        },
        {
            "Word": "Paradigm",
            "Difficulty": "Extreme"
        },
        {
            "Word": "Paraphernalia",
            "Difficulty": "Extreme"
        },
        {
            "Word": "Parliamentary",
            "Difficulty": "Hard"
        },
        {
            "Word": "Paroxysm",
            "Difficulty": "Extreme"
        },
        {
            "Word": "Perspicacious",
            "Difficulty": "Extreme"
        },
        {
            "Word": "Pessimistic",
            "Difficulty": "Hard"
        },
        {
            "Word": "Cacophony",
            "Difficulty": "Hard"
        },
        {
            "Word": "Phenomenon",
            "Difficulty": "Hard"
        },
        {
            "Word": "Nomenclature",
            "Difficulty": "Hard"
        },
        {
            "Word": "Pneumatic",
            "Difficulty": "Hard"
        },
        {
            "Word": "Polemic",
            "Difficulty": "Hard"
        },
        {
            "Word": "Polydactyly",
            "Difficulty": "Hard"
        },
        {
            "Word": "Prognostication",
            "Difficulty": "Extreme"
        },
        {
            "Word": "Psychological",
            "Difficulty": "Hard"
        },
        {
            "Word": "Puerile",
            "Difficulty": "Hard"
        },
        {
            "Word": "Pulchritudinous",
            "Difficulty": "Extreme"
        },
        {
            "Word": "Pusillanimous",
            "Difficulty": "Extreme"
        },
        {
            "Word": "Pygmy",
            "Difficulty": "Hard"
        },
        {
            "Word": "Querimony",
            "Difficulty": "Hard"
        },
        {
            "Word": "Quixotry",
            "Difficulty": "Extreme"
        },
        {
            "Word": "Rambunctious",
            "Difficulty": "Hard"
        },
        {
            "Word": "Rehabilitation",
            "Difficulty": "Hard"
        },
        {
            "Word": "Rendezvous",
            "Difficulty": "Hard"
        },
        {
            "Word": "Rhinorrhagia",
            "Difficulty": "Extreme"
        },
        {
            "Word": "Sagacious",
            "Difficulty": "Hard"
        },
        {
            "Word": "Sarcophagus",
            "Difficulty": "Hard"
        },
        {
            "Word": "Sequoia",
            "Difficulty": "Extreme"
        },
        {
            "Word": "Serendipity",
            "Difficulty": "Extreme"
        },
        {
            "Word": "Sesquipedalian",
            "Difficulty": "Extreme"
        },
        {
            "Word": "Silhouette",
            "Difficulty": "Hard"
        },
        {
            "Word": "Soliloquy",
            "Difficulty": "Extreme"
        },
        {
            "Word": "Sovereignty",
            "Difficulty": "Hard"
        },
        {
            "Word": "Subpoena",
            "Difficulty": "Extreme"
        },
        {
            "Word": "Subterranean",
            "Difficulty": "Hard"
        },
        {
            "Word": "Supererogatory",
            "Difficulty": "Extreme"
        },
        {
            "Word": "Superferromagnetism",
            "Difficulty": "Extreme"
        },
        {
            "Word": "Supersede/Supercede",
            "Difficulty": "Hard"
        },
        {
            "Word": "Susurration",
            "Difficulty": "Extreme"
        },
        {
            "Word": "Symbiosis",
            "Difficulty": "Hard"
        },
        {
            "Word": "Syzygy",
            "Difficulty": "Extreme"
        },
        {
            "Word": "Thalassophobia",
            "Difficulty": "Extreme"
        },
        {
            "Word": "Therapeutic",
            "Difficulty": "Hard"
        },
        {
            "Word": "Utilitarianism",
            "Difficulty": "Extreme"
        },
        {
            "Word": "Verbatim",
            "Difficulty": "Hard"
        },
        {
            "Word": "Vexatious",
            "Difficulty": "Hard"
        },
        {
            "Word": "Vulnerability",
            "Difficulty": "Hard"
        },
        {
            "Word": "Worcestershire",
            "Difficulty": "Extreme"
        },
        {
            "Word": "Acetaminophen",
            "Difficulty": "Extreme"
        },
        {
            "Word": "Achromatophil",
            "Difficulty": "Extreme"
        },
        {
            "Word": "Achromatophilia",
            "Difficulty": "Extreme"
        },
        {
            "Word": "Baccalaureate",
            "Difficulty": "Extreme"
        },
        {
            "Word": "Batrachophobia",
            "Difficulty": "Extreme"
        },
        {
            "Word": "Bogolanfini",
            "Difficulty": "Extreme"
        },
        {
            "Word": "Compartmentalization/Compartmentalisation",
            "Difficulty": "Extreme"
        },
        {
            "Word": "Jurisprudence",
            "Difficulty": "Extreme"
        },
        {
            "Word": "Neuropsychological",
            "Difficulty": "Extreme"
        },
        {
            "Word": "Portmanteau",
            "Difficulty": "Extreme"
        },
        {
            "Word": "Prestidigitation",
            "Difficulty": "Extreme"
        },
        {
            "Word": "Quasquicentennial",
            "Difficulty": "Extreme"
        },
        {
            "Word": "Subcompartmentalization/Subcompartmentalisation",
            "Difficulty": "Extreme"
        },
        {
            "Word": "Verisimilitude",
            "Difficulty": "Extreme"
        },
        {
            "Word": "Autothaumaturgist",
            "Difficulty": "Impossible"
        },
        {
            "Word": "Bourgeoisie",
            "Difficulty": "Impossible"
        },
        {
            "Word": "Bourgeoisification",
            "Difficulty": "Impossible"
        },
        {
            "Word": "Hippopotomonstrosesquippedaliophobia/Hippopotomonstrosesquipedaliophobia",
            "Difficulty": "Impossible"
        },
        {
            "Word": "Institutionalization/Institutionalisation",
            "Difficulty": "Impossible"
        },
        {
            "Word": "Quindecasyllabic",
            "Difficulty": "Impossible"
        },
        {
            "Word": "Quoddamodotative",
            "Difficulty": "Impossible"
        },
        {
            "Word": "Adrenocorticotrophin/Adrenocorticotropin",
            "Difficulty": "Impossible"
        },
        {
            "Word": "Anthropomorphization/Anthropomorphisation",
            "Difficulty": "Impossible"
        },
        {
            "Word": "Arthroereisis",
            "Difficulty": "Impossible"
        },
        {
            "Word": "Convolvulaceous",
            "Difficulty": "Impossible"
        },
        {
            "Word": "Ethnomethodology",
            "Difficulty": "Impossible"
        },
        {
            "Word": "Floccinaucinihilipilification",
            "Difficulty": "Impossible"
        },
        {
            "Word": "Gastroenterologist",
            "Difficulty": "Impossible"
        },
        {
            "Word": "Glyceraldehyde",
            "Difficulty": "Impossible"
        },
        {
            "Word": "Honorificabilitudinity",
            "Difficulty": "Impossible"
        },
        {
            "Word": "Hypoparathyroidism",
            "Difficulty": "Impossible"
        },
        {
            "Word": "Oligonucleotide",
            "Difficulty": "Impossible"
        },
        {
            "Word": "Otorhinolaryngological",
            "Difficulty": "Impossible"
        },
        {
            "Word": "Parallelogrammatic",
            "Difficulty": "Impossible"
        },
        {
            "Word": "Pneumoencephalography",
            "Difficulty": "Impossible"
        },
        {
            "Word": "Polyphiloprogenitive",
            "Difficulty": "Impossible"
        },
        {
            "Word": "Pseudopseudohypoparathyroidism",
            "Difficulty": "Impossible"
        },
        {
            "Word": "Psychoneuroendocrinological",
            "Difficulty": "Impossible"
        },
        {
            "Word": "Psychoneuroimmunology",
            "Difficulty": "Impossible"
        },
        {
            "Word": "Psychophysicotherapeutics",
            "Difficulty": "Impossible"
        },
        {
            "Word": "Radiometeorograph",
            "Difficulty": "Impossible"
        },
        {
            "Word": "Supercalifragilisticexpialidocious",
            "Difficulty": "Impossible"
        },
        {
            "Word": "Xylotypographic",
            "Difficulty": "Impossible"
        }
    ]
}